file_binary/__init__.py
file_binary/binary_array_file.py
file_binary/binary_average_file.py
file_binary/binary_matrix_file.py
file_binary/binary_to_txt.py
file_binary/fb.py
file_binary-0.8.0.dist-info/LICENSE
file_binary-0.8.0.dist-info/WHEEL
file_binary-0.8.0.dist-info/METADATA
file_binary-0.8.0.dist-info/RECORD
