Metadata-Version: 2.1
Name: file-binary
Version: 0.8.0
Summary: File Binary is a package with some tools to help you with binary files
Home-page: https://github.com/MatheusRamo/file_binary
Keywords: text
Author: matheus
Author-email: geof.matheus@gmail.com
Requires-Python: >=3.9,<4.0
Classifier: Programming Language :: Python :: 3
Classifier: Programming Language :: Python :: 3.10
Classifier: Programming Language :: Python :: 3.9
Requires-Dist: numpy (>=1.22.3,<2.0.0)
Project-URL: Repository, https://github.com/MatheusRamo/file_binary
